Metadata-Version: 1.1
Name: namemapping
Version: 0.1.0.dev1
Summary: A Python project uses Yahoo BOSS API to unify company names
Home-page: https://github.com/biwa7636/namemapping
Author: Bin Wang & Daniel Sweeney
Author-email: binwang.cu@gmail.com
License: MIT
Keywords: yahoo api boss oauth2
Platform: UNKNOWN
Classifier: Development Status :: 3 - Alpha
Classifier: Intended Audience :: Developers
Classifier: License :: OSI Approved :: MIT License
Classifier: Programming Language :: Python :: 2.6
Classifier: Programming Language :: Python :: 2.7
